boombig/__init__.py
boombig/config.py
boombig/main.py
boombig-0.3.dist-info/LICENSE
boombig-0.3.dist-info/METADATA
boombig-0.3.dist-info/WHEEL
boombig-0.3.dist-info/top_level.txt
boombig-0.3.dist-info/RECORD
