Metadata-Version: 2.1
Name: boombig
Version: 0.3
Summary: boombing a Library Python
Home-page: https://github.com/OnlyRad/Boombers
Author: Mohammad and Amir
Author-email: mohammadmehrabi175@gmail.com
Keywords: bot,sms,boombers,boomber,boomb
Classifier: Programming Language :: Python :: 3.6
Classifier: Programming Language :: Python :: 3.7
Classifier: Programming Language :: Python :: 3.8
Classifier: Programming Language :: Python :: 3.9
Classifier: Programming Language :: Python :: 3.10
Classifier: Programming Language :: Python :: 3.11
Classifier: Programming Language :: Python :: 3.12
Classifier: License :: OSI Approved :: MIT License
Requires-Python: ~=3.6
License-File: LICENSE
